marbl/__init__.py
marbl/__version__.py
marbl-0.0.0.dist-info/DESCRIPTION.rst
marbl-0.0.0.dist-info/METADATA
marbl-0.0.0.dist-info/RECORD
marbl-0.0.0.dist-info/WHEEL
marbl-0.0.0.dist-info/metadata.json
marbl-0.0.0.dist-info/top_level.txt
