Metadata-Version: 2.0
Name: marbl
Version: 0.0.0
Summary: an asyncio microservices framework
Home-page: https://github.com/jeremyarr/marbl
Author: Jeremy Arr
Author-email: jeremyarr@gmail.com
License: MIT
Platform: UNKNOWN
Classifier: Development Status :: 2 - Pre-Alpha
Classifier: License :: OSI Approved :: MIT License
Classifier: Intended Audience :: Developers
Classifier: Programming Language :: Python :: 3.6
